{
    "name": "Networking Dev",
    "dockerComposeFile": [
        "../docker-compose.yml"
    ],
    "service": "server", // VSCode attaches to the server container
    "workspaceFolder": "/app",
    "customizations": {
        "vscode": {
            "extensions": [
                "llvm-vs-code-extensions.vscode-clangd",
                "ms-vscode.cmake-tools",
                "ms-vscode.cpptools",
                "ms-vscode.makefile-tools",
                "ms-azuretools.vscode-docker"
            ]
        }
    },
    "features": {
        "ghcr.io/devcontainers/features/git:1": {}
    },
    "remoteUser": "root",
    "init": true
}